DDM/__init__.py
DDM/api/__init__.py
DDM/api/cdkey_client.py
DDM/models/__init__.py
DDM/models/cdkey_heartbeat_request.py
DDM/models/cdkey_heartbeat_response.py
DDM/models/cdkey_login_request.py
DDM/models/cdkey_login_response.py
DDM/models/config.py
DDM/models/session.py
DDM/utils/__init__.py
DDM/utils/device_info.py
DDM/utils/helpers.py
ddm_hd-1.0.0.dist-info/licenses/LICENSE
ddm_hd-1.0.0.dist-info/METADATA
ddm_hd-1.0.0.dist-info/WHEEL
ddm_hd-1.0.0.dist-info/top_level.txt
ddm_hd-1.0.0.dist-info/RECORD
